coreason_signal/__init__.py
coreason_signal/api.py
coreason_signal/config.py
coreason_signal/edge_agent/__init__.py
coreason_signal/edge_agent/reflex_engine.py
coreason_signal/edge_agent/vector_store.py
coreason_signal/main.py
coreason_signal/schemas.py
coreason_signal/service.py
coreason_signal/sila/__init__.py
coreason_signal/sila/features.py
coreason_signal/sila/server.py
coreason_signal/soft_sensor/__init__.py
coreason_signal/soft_sensor/engine.py
coreason_signal/streaming/__init__.py
coreason_signal/streaming/flight_server.py
coreason_signal/twin/__init__.py
coreason_signal/twin/syncer.py
coreason_signal/utils/__init__.py
coreason_signal/utils/logger.py
coreason_signal-0.4.0.dist-info/METADATA
coreason_signal-0.4.0.dist-info/WHEEL
coreason_signal-0.4.0.dist-info/entry_points.txt
coreason_signal-0.4.0.dist-info/licenses/LICENSE
coreason_signal-0.4.0.dist-info/licenses/NOTICE
coreason_signal-0.4.0.dist-info/RECORD
