Metadata-Version: 2.4
Name: coreason_signal
Version: 0.4.0
Summary: coreason-signal
License: # The Prosperity Public License 3.0.0
License-File: LICENSE
License-File: NOTICE
Author: Gowtham A Rao
Author-email: gowtham.rao@coreason.ai
Requires-Python: >=3.11
Classifier: License :: Other/Proprietary License
Classifier: Programming Language :: Python :: 3.12
Classifier: Operating System :: OS Independent
Requires-Dist: aiofiles (>=25.1.0,<26.0.0)
Requires-Dist: anyio (>=4.12.1,<5.0.0)
Requires-Dist: coreason-identity (>=0.4.2,<0.5.0)
Requires-Dist: cryptography (>=46.0.4,<47.0.0)
Requires-Dist: fastapi (>=0.115.0,<0.116.0)
Requires-Dist: fastembed (>=0.7.4,<0.8.0)
Requires-Dist: httpx (>=0.28.1,<0.29.0)
Requires-Dist: lancedb (>=0.27.1,<0.28.0)
Requires-Dist: loguru (>=0.7.2,<0.8.0)
Requires-Dist: onnxruntime (>=1.23.2,<2.0.0)
Requires-Dist: pyarrow (>=23.0.0,<24.0.0)
Requires-Dist: pydantic (>=2.12.5,<3.0.0)
Requires-Dist: pydantic-settings (>=2.12.0,<3.0.0)
Requires-Dist: sila2 (>=0.14.0,<0.15.0)
Requires-Dist: uvicorn[standard] (>=0.30.0,<0.31.0)
Project-URL: Documentation, https://github.com/CoReason-AI/coreason_signal
Project-URL: Homepage, https://github.com/CoReason-AI/coreason_signal
Project-URL: Repository, https://github.com/CoReason-AI/coreason_signal
